[
  {
    "symbolicName": "jre",
    "version": {
      "major": 1,
      "minor": 0,
      "micro": 0,
      "qualifier": ""
    },
    "jarFileFingerprint": "14b2318e78e9bfdb9d3e8733616367d67dd4b72a",
    "jarFileModificationDate": "2014-03-18T14:47:34+07:00",
    "location": "/Library/Java/JavaVirtualMachines/jdk1.8.0_05.jdk/Contents/Home/jre/lib/ext/localedata.jar",
    "javaRuntime": true
  },
  {
    "symbolicName": "jre",
    "version": {
      "major": 1,
      "minor": 0,
      "micro": 0,
      "qualifier": ""
    },
    "jarFileFingerprint": "9a1284417f00f1a4c77e67d71a6fbea2eeaf5d7c",
    "jarFileModificationDate": "2014-03-18T14:47:34+07:00",
    "location": "/Library/Java/JavaVirtualMachines/jdk1.8.0_05.jdk/Contents/Home/jre/lib/jce.jar",
    "javaRuntime": true
  },
  {
    "symbolicName": "jre",
    "version": {
      "major": 1,
      "minor": 0,
      "micro": 0,
      "qualifier": ""
    },
    "jarFileFingerprint": "a85d5af49e138a0adefc26bf22d2cfc8c754e6dd",
    "jarFileModificationDate": "2013-08-08T09:11:25+07:00",
    "location": "/System/Library/Java/Extensions/jai_codec.jar",
    "javaRuntime": true
  },
  {
    "symbolicName": "jre",
    "version": {
      "major": 1,
      "minor": 0,
      "micro": 0,
      "qualifier": ""
    },
    "jarFileFingerprint": "3bc82c5707e80b282524f41eb633f7abf03b23b6",
    "jarFileModificationDate": "2014-03-18T14:47:34+07:00",
    "location": "/Library/Java/JavaVirtualMachines/jdk1.8.0_05.jdk/Contents/Home/jre/lib/ext/sunec.jar",
    "javaRuntime": true
  },
  {
    "symbolicName": "jre",
    "version": {
      "major": 1,
      "minor": 0,
      "micro": 0,
      "qualifier": ""
    },
    "jarFileFingerprint": "096d28ce6e0ff470aa8ef77a8aa504a9e0e141dc",
    "jarFileModificationDate": "2014-03-18T14:47:34+07:00",
    "location": "/Library/Java/JavaVirtualMachines/jdk1.8.0_05.jdk/Contents/Home/jre/lib/jsse.jar",
    "javaRuntime": true
  },
  {
    "symbolicName": "jre",
    "version": {
      "major": 1,
      "minor": 0,
      "micro": 0,
      "qualifier": ""
    },
    "jarFileFingerprint": "f0175c4c28f08b9236108499c33d6542c0bcd8b4",
    "jarFileModificationDate": "2013-08-08T09:15:41+07:00",
    "location": "/System/Library/Java/Extensions/j3daudio.jar",
    "javaRuntime": true
  },
  {
    "symbolicName": "jre",
    "version": {
      "major": 1,
      "minor": 0,
      "micro": 0,
      "qualifier": ""
    },
    "jarFileFingerprint": "af0c71e14ca402301689c88c498d6eb322af587c",
    "jarFileModificationDate": "2014-03-18T14:47:34+07:00",
    "location": "/Library/Java/JavaVirtualMachines/jdk1.8.0_05.jdk/Contents/Home/jre/lib/jfr.jar",
    "javaRuntime": true
  },
  {
    "symbolicName": "jre",
    "version": {
      "major": 1,
      "minor": 0,
      "micro": 0,
      "qualifier": ""
    },
    "jarFileFingerprint": "4f4081b69df48f293cf72c65d2cbe0108fbd1539",
    "jarFileModificationDate": "2014-03-18T14:47:34+07:00",
    "location": "/Library/Java/JavaVirtualMachines/jdk1.8.0_05.jdk/Contents/Home/jre/lib/ext/sunpkcs11.jar",
    "javaRuntime": true
  },
  {
    "symbolicName": "jre",
    "version": {
      "major": 1,
      "minor": 0,
      "micro": 0,
      "qualifier": ""
    },
    "jarFileFingerprint": "010262dc3ab6da57eaef700d8d7d134f39fc09d7",
    "jarFileModificationDate": "2014-03-18T14:47:34+07:00",
    "location": "/Library/Java/JavaVirtualMachines/jdk1.8.0_05.jdk/Contents/Home/jre/lib/ext/zipfs.jar",
    "javaRuntime": true
  },
  {
    "symbolicName": "jre",
    "version": {
      "major": 1,
      "minor": 0,
      "micro": 0,
      "qualifier": ""
    },
    "jarFileFingerprint": "5e2c12ffab605a78f773e42b2497a9569316346f",
    "jarFileModificationDate": "2014-03-18T14:47:34+07:00",
    "location": "/Library/Java/JavaVirtualMachines/jdk1.8.0_05.jdk/Contents/Home/jre/lib/ext/sunjce_provider.jar",
    "javaRuntime": true
  },
  {
    "symbolicName": "jre",
    "version": {
      "major": 1,
      "minor": 0,
      "micro": 0,
      "qualifier": ""
    },
    "jarFileFingerprint": "3992b52876ea5c35473e170f78781d8be91c6dd2",
    "jarFileModificationDate": "2013-11-24T06:15:25+07:00",
    "location": "/System/Library/Java/Extensions/QTJava.zip",
    "javaRuntime": true
  },
  {
    "symbolicName": "jre",
    "version": {
      "major": 1,
      "minor": 0,
      "micro": 0,
      "qualifier": ""
    },
    "jarFileFingerprint": "e7533ef29283d456ddcc700ad2ccdd0c3452e464",
    "jarFileModificationDate": "2013-08-08T09:15:41+07:00",
    "location": "/System/Library/Java/Extensions/j3dutils.jar",
    "javaRuntime": true
  },
  {
    "symbolicName": "jre",
    "version": {
      "major": 1,
      "minor": 0,
      "micro": 0,
      "qualifier": ""
    },
    "jarFileFingerprint": "63fbdd9c7e93573cc15ee487950217886be2aef6",
    "jarFileModificationDate": "2013-11-02T18:10:26+07:00",
    "location": "/System/Library/Java/Extensions/dns_sd.jar",
    "javaRuntime": true
  },
  {
    "symbolicName": "jre",
    "version": {
      "major": 1,
      "minor": 0,
      "micro": 0,
      "qualifier": ""
    },
    "jarFileFingerprint": "d57b4588c1c302ad017b0cf25de95dfb1b22e8fc",
    "jarFileModificationDate": "2013-11-02T18:10:22+07:00",
    "location": "/System/Library/Java/Extensions/MRJToolkit.jar",
    "javaRuntime": true
  },
  {
    "symbolicName": "jre",
    "version": {
      "major": 1,
      "minor": 0,
      "micro": 0,
      "qualifier": ""
    },
    "jarFileFingerprint": "e025051fbcb83787ec5bc90c7b9b6c9fcd4e5c55",
    "jarFileModificationDate": "2014-03-18T14:47:34+07:00",
    "location": "/Library/Java/JavaVirtualMachines/jdk1.8.0_05.jdk/Contents/Home/jre/lib/resources.jar",
    "javaRuntime": true
  },
  {
    "symbolicName": "forms-1.3.0",
    "version": {
      "major": -1,
      "minor": -1,
      "micro": -1,
      "qualifier": ""
    },
    "jarFileFingerprint": "16a13056429fe1549076d25c7e5359b3f99b805f",
    "jarFileModificationDate": "2014-05-18T14:23:55+07:00",
    "location": "/Users/ferysurya/Downloads/a/BookBay/forms-1.3.0.jar",
    "javaRuntime": false
  },
  {
    "symbolicName": "jre",
    "version": {
      "major": 1,
      "minor": 0,
      "micro": 0,
      "qualifier": ""
    },
    "jarFileFingerprint": "3688828da27c14972d47e818200bd8ddbe5ef026",
    "jarFileModificationDate": "2014-03-18T14:47:34+07:00",
    "location": "/Library/Java/JavaVirtualMachines/jdk1.8.0_05.jdk/Contents/Home/jre/lib/ext/nashorn.jar",
    "javaRuntime": true
  },
  {
    "symbolicName": "jre",
    "version": {
      "major": 1,
      "minor": 0,
      "micro": 0,
      "qualifier": ""
    },
    "jarFileFingerprint": "297aea888a3f3d11e11d81a4e940571ed892551e",
    "jarFileModificationDate": "2014-03-18T14:47:35+07:00",
    "location": "/Library/Java/JavaVirtualMachines/jdk1.8.0_05.jdk/Contents/Home/jre/lib/rt.jar",
    "javaRuntime": true
  },
  {
    "symbolicName": "jre",
    "version": {
      "major": 1,
      "minor": 0,
      "micro": 0,
      "qualifier": ""
    },
    "jarFileFingerprint": "5db3bc5b2e552949a492443d9499d9073e277f27",
    "jarFileModificationDate": "2014-03-18T14:47:34+07:00",
    "location": "/Library/Java/JavaVirtualMachines/jdk1.8.0_05.jdk/Contents/Home/jre/lib/charsets.jar",
    "javaRuntime": true
  },
  {
    "symbolicName": "jre",
    "version": {
      "major": 1,
      "minor": 0,
      "micro": 0,
      "qualifier": ""
    },
    "jarFileFingerprint": "21240ab7c12f378058cbb7a9b2f5b762dd30e1b8",
    "jarFileModificationDate": "2013-08-08T09:11:25+07:00",
    "location": "/System/Library/Java/Extensions/jai_core.jar",
    "javaRuntime": true
  },
  {
    "symbolicName": "jre",
    "version": {
      "major": 1,
      "minor": 0,
      "micro": 0,
      "qualifier": ""
    },
    "jarFileFingerprint": "005810d865dab9bd200ea485d0e44c18a329aa26",
    "jarFileModificationDate": "2013-08-08T09:15:41+07:00",
    "location": "/System/Library/Java/Extensions/vecmath.jar",
    "javaRuntime": true
  },
  {
    "symbolicName": "com.mysql.jdbc",
    "version": {
      "major": 5,
      "minor": 1,
      "micro": 30,
      "qualifier": ""
    },
    "jarFileFingerprint": "50aa5073896609b6b8c5e484c7671449daccf94c",
    "jarFileModificationDate": "2014-05-18T14:23:55+07:00",
    "location": "/Users/ferysurya/Downloads/a/BookBay/libs/mysql-connector-java-5.1.30-bin.jar",
    "javaRuntime": false
  },
  {
    "symbolicName": "jre",
    "version": {
      "major": 1,
      "minor": 0,
      "micro": 0,
      "qualifier": ""
    },
    "jarFileFingerprint": "c5d7b7bfab9b433c4b62aebbe76a564b6bcf8192",
    "jarFileModificationDate": "2013-08-08T09:11:00+07:00",
    "location": "/System/Library/Java/Extensions/mlibwrapper_jai.jar",
    "javaRuntime": true
  },
  {
    "symbolicName": "jre",
    "version": {
      "major": 1,
      "minor": 0,
      "micro": 0,
      "qualifier": ""
    },
    "jarFileFingerprint": "51dbde992ee8e0ee2e9e1be38fcc6d3295ebc66e",
    "jarFileModificationDate": "2013-08-08T09:16:58+07:00",
    "location": "/System/Library/Java/Extensions/AppleScriptEngine.jar",
    "javaRuntime": true
  },
  {
    "symbolicName": "jre",
    "version": {
      "major": 1,
      "minor": 0,
      "micro": 0,
      "qualifier": ""
    },
    "jarFileFingerprint": "2a86052cce150823174cfde7208cf3a71aba4016",
    "jarFileModificationDate": "2014-03-18T14:47:34+07:00",
    "location": "/Library/Java/JavaVirtualMachines/jdk1.8.0_05.jdk/Contents/Home/jre/lib/ext/dnsns.jar",
    "javaRuntime": true
  },
  {
    "symbolicName": "jre",
    "version": {
      "major": 1,
      "minor": 0,
      "micro": 0,
      "qualifier": ""
    },
    "jarFileFingerprint": "24e0571e05e3ea75ffcb79cfb170aee4d723b656",
    "jarFileModificationDate": "2014-03-18T01:45:24+07:00",
    "location": "/Library/Java/JavaVirtualMachines/jdk1.8.0_05.jdk/Contents/Home/jre/lib/ext/jfxrt.jar",
    "javaRuntime": true
  },
  {
    "symbolicName": "jre",
    "version": {
      "major": 1,
      "minor": 0,
      "micro": 0,
      "qualifier": ""
    },
    "jarFileFingerprint": "7f517adf74fb6a885c444768f6ce5d724e8a8385",
    "jarFileModificationDate": "2014-03-18T14:47:34+07:00",
    "location": "/Library/Java/JavaVirtualMachines/jdk1.8.0_05.jdk/Contents/Home/jre/lib/ext/cldrdata.jar",
    "javaRuntime": true
  },
  {
    "symbolicName": "jre",
    "version": {
      "major": 1,
      "minor": 0,
      "micro": 0,
      "qualifier": ""
    },
    "jarFileFingerprint": "06b897f357f111e205017803b1d10f972e8f1075",
    "jarFileModificationDate": "2013-08-08T09:15:41+07:00",
    "location": "/System/Library/Java/Extensions/j3dcore.jar",
    "javaRuntime": true
  }
]